oanda_candles/__init__.py
oanda_candles/candle.py
oanda_candles/candle_client.py
oanda_candles/candle_collector.py
oanda_candles/candle_meister.py
oanda_candles/candle_requester.py
oanda_candles/gran.py
oanda_candles/gran_unit.py
oanda_candles/ohlc.py
oanda_candles/quote_kind.py
oanda_candles-0.1.0.dist-info/LICENSE
oanda_candles-0.1.0.dist-info/WHEEL
oanda_candles-0.1.0.dist-info/METADATA
oanda_candles-0.1.0.dist-info/RECORD
