Metadata-Version: 2.1
Name: oanda-candles
Version: 0.1.0
Summary: Oanda forex candle API built on top of oandapyV20
Home-page: https://github.com/aallaire/oanda-candles
License: Apache-2.0
Author: Andrew Allaire
Author-email: andrew.allaire@gmail.com
Requires-Python: >=3.5,<4.0
Classifier: License :: OSI Approved :: Apache Software License
Classifier: Programming Language :: Python :: 3
Classifier: Programming Language :: Python :: 3.5
Classifier: Programming Language :: Python :: 3.6
Classifier: Programming Language :: Python :: 3.7
Classifier: Programming Language :: Python :: 3.8
Requires-Dist: forex-types (>=0.0.6,<0.0.7)
Requires-Dist: magic-kind (>=0.2.2,<0.3.0)
Requires-Dist: oandapyV20 (>=0.6.3,<0.7.0)
Requires-Dist: requests (>=2.23.0,<3.0.0)
Requires-Dist: time-int (>=0.0.9,<0.0.10)
Project-URL: Repository, https://github.com/aallaire/oanda-candles
